nova_act_mcp_server-3.2.2.dist-info/licenses/LICENSE
nova_mcp_server/__init__.py
nova_mcp_server/__main__.py
nova_mcp_server/config.py
nova_mcp_server/main_cli.py
nova_mcp_server/session_manager.py
nova_mcp_server/utils.py
nova_mcp_server/utils_enhanced.py
nova_mcp_server/tools/__init__.py
nova_mcp_server/tools/actions_end.py
nova_mcp_server/tools/actions_execute.py
nova_mcp_server/tools/actions_inspect.py
nova_mcp_server/tools/actions_start.py
nova_mcp_server/tools/browser_control.py
nova_mcp_server/tools/file_transfer.py
nova_mcp_server/tools/log_management.py
nova_mcp_server/tools/session_listing.py
nova_act_mcp_server-3.2.2.dist-info/METADATA
nova_act_mcp_server-3.2.2.dist-info/WHEEL
nova_act_mcp_server-3.2.2.dist-info/entry_points.txt
nova_act_mcp_server-3.2.2.dist-info/top_level.txt
nova_act_mcp_server-3.2.2.dist-info/RECORD
