Metadata-Version: 2.4
Name: nova-act-mcp-server
Version: 3.2.2
Summary: An MCP server providing tools to control web browsers using the Amazon Nova Act SDK
Author-email: Jacob Taunton <jandrewt82@gmail.com>
License-Expression: MIT
Project-URL: Homepage, https://github.com/madtank/nova-act-mcp
Project-URL: Bug Tracker, https://github.com/madtank/nova-act-mcp/issues
Requires-Python: >=3.10
License-File: LICENSE
Requires-Dist: httpx>=0.28.1
Requires-Dist: mcp>=1.6.0
Requires-Dist: pydantic>=2.11.4
Requires-Dist: nova-act>=1.0.2579.0
Requires-Dist: playwright==1.48.0
Requires-Dist: fastmcp==2.2.5
Requires-Dist: asyncio-extras>=1.3.2
Requires-Dist: rich>=14.0.0
Requires-Dist: structlog>=25.3.0
Requires-Dist: tenacity>=9.1.2
Requires-Dist: uvloop>=0.21.0; sys_platform != "win32"
Requires-Dist: python-dotenv>=1.0.0
Requires-Dist: pytest>=8.3.5
Provides-Extra: dev
Requires-Dist: pytest>=8.3.5; extra == "dev"
Requires-Dist: pytest-asyncio>=0.26.0; extra == "dev"
Requires-Dist: black>=25.1.0; extra == "dev"
Requires-Dist: isort>=6.0.1; extra == "dev"
Requires-Dist: mypy>=1.15.0; extra == "dev"
Requires-Dist: ruff>=0.11.7; extra == "dev"
Requires-Dist: pytest-dotenv>=0.5.2; extra == "dev"
Provides-Extra: sse
Dynamic: license-file
